sifenpy/__init__.py
sifenpy/client/__init__.py
sifenpy/models/__init__.py
sifenpy/signing/__init__.py
sifenpy/utils/__init__.py
sifenpy-0.1.1.dist-info/METADATA
sifenpy-0.1.1.dist-info/WHEEL
sifenpy-0.1.1.dist-info/licenses/LICENSE
sifenpy-0.1.1.dist-info/RECORD
