Metadata-Version: 2.4
Name: sifenpy
Version: 0.1.1
Summary: Biblioteca de Python para integración con la sifen
License: MIT
License-File: LICENSE
Author: tetotille
Author-email: jltilleriam@gmail.com
Requires-Python: >=3.12,<4.0.0
Classifier: Programming Language :: Python :: 3
Classifier: License :: OSI Approved :: MIT License
Classifier: Operating System :: OS Independent
Classifier: Development Status :: 1 - Planning
Classifier: Intended Audience :: Developers
Classifier: Topic :: Office/Business :: Financial :: Accounting
Requires-Dist: cryptography (>=46.0.3,<47.0.0)
Requires-Dist: lxml (>=6.0.2,<7.0.0)
Requires-Dist: pydantic (>=2.12.5,<3.0.0)
Requires-Dist: requests (>=2.32.5,<3.0.0)
Project-URL: Bug Tracker, https://github.com/tetotille/sifenpy/issues
Project-URL: Homepage, https://github.com/tetotille/sifenpy
